.environment.yml
.travis.yml
AUTHORS
ChangeLog
Readme.rst
requirements-dev.txt
requirements.txt
setup.cfg
setup.py
tox.ini
tests/unit/test_methods.py
trakt_aiohttp/__init__.py
trakt_aiohttp/aiohttp_device.py
trakt_aiohttp.egg-info/PKG-INFO
trakt_aiohttp.egg-info/SOURCES.txt
trakt_aiohttp.egg-info/dependency_links.txt
trakt_aiohttp.egg-info/not-zip-safe
trakt_aiohttp.egg-info/pbr.json
trakt_aiohttp.egg-info/requires.txt
trakt_aiohttp.egg-info/top_level.txt