Metadata-Version: 1.1
Name: trakt-aiohttp
Version: 1.0.2.dev1
Summary: Trakt.tv python3.5+ library
Home-page: http://github.com/XayOn/trakt_aiohttp
Author: David Francos Cuartero
Author-email: opensource@davidfrancos.net
License: GPL3+
Keywords: trakt
Platform: UNKNOWN
Classifier: Development Status :: 4 - Beta
Classifier: Environment :: Console
Classifier: Intended Audience :: Information Technology
Classifier: License :: OSI Approved :: GNU General Public License v3 (GPLv3)
Classifier: Operating System :: OS Independent
Classifier: Programming Language :: Python
